tensorflow_chatbots/__init__.py
tensorflow_chatbots/tsb/__init__.py
tensorflow_chatbots/tsb/callback.py
tensorflow_chatbots/ttb/__init__.py
tensorflow_chatbots/ttb/callback.py
tensorflow_chatbots/variableholder/__init__.py
tensorflow_chatbots/variableholder/variableholder.py
Tensorflow_ChatBots-0.0.12.dist-info/METADATA
Tensorflow_ChatBots-0.0.12.dist-info/WHEEL
Tensorflow_ChatBots-0.0.12.dist-info/top_level.txt
Tensorflow_ChatBots-0.0.12.dist-info/RECORD
