Metadata-Version: 2.1
Name: Tensorflow-ChatBots
Version: 0.0.12
Summary: ChatBots supporting TensorFlow
Home-page: https://github.com/Yeachan-Heo/Tensorflow-ChatBots
Author: Yeachan-Heo
Author-email: hurrc04@gmail.com
License: MIT
Platform: UNKNOWN
Requires-Dist: tensorflow
Requires-Dist: gym
Requires-Dist: numpy
Requires-Dist: numba
Requires-Dist: matplotlib
Requires-Dist: slacker
Requires-Dist: python-telegram-bot
